termcontrol/Makefile
termcontrol/__init__.py
termcontrol/cli.py
termcontrol/hijack
termcontrol/hijack.c
termcontrol-2021.5.2.dist-info/METADATA
termcontrol-2021.5.2.dist-info/WHEEL
termcontrol-2021.5.2.dist-info/entry_points.txt
termcontrol-2021.5.2.dist-info/top_level.txt
termcontrol-2021.5.2.dist-info/RECORD
