Metadata-Version: 2.1
Name: termcontrol
Version: 2021.5.2
Summary: Terminal TTY IO Control
Home-page: https://github.com/axiros/termcontrol
Author: Gunther Klessinger
Author-email: gklessinger@gmx.de
License: BSD
Keywords: fzf,terminal,tty,pty,IO,hijack
Platform: UNKNOWN
Classifier: Development Status :: 3 - Alpha
Classifier: Intended Audience :: Developers
Classifier: Operating System :: POSIX
Classifier: License :: OSI Approved :: BSD License
Classifier: Topic :: Terminals
Classifier: Topic :: Utilities
Classifier: Topic :: System :: Shells
Classifier: Topic :: System :: System Shells
Classifier: Programming Language :: Python :: 2
Classifier: Environment :: Console
Classifier: Programming Language :: Python :: 2.7
Classifier: Programming Language :: Python :: 3
Classifier: Programming Language :: C
